resmod/__init__.py
resmod/plotting/__init__.py
resmod/plotting/interact_plot.py
resmod/sem/__init__.py
resmod/sem/orthogonalize.py
resmod/single/__init__.py
resmod/single/residual_center.py
resmod/single/three_center.py
resmod/slopes/__init__.py
resmod/slopes/simple_slopes.py
resmod-0.2.5.dist-info/licenses/LICENSE
resmod-0.2.5.dist-info/METADATA
resmod-0.2.5.dist-info/WHEEL
resmod-0.2.5.dist-info/top_level.txt
resmod-0.2.5.dist-info/RECORD
