Metadata-Version: 2.4
Name: resmod
Version: 0.2.5
Summary: A package for deriving orthogonalized interaction terms, reporting interaction analyses, and visualization of interactions
Author-email: "Drew E. Winters, PhD." <drewEwinters@gmail.com>
License: MIT
Project-URL: Homepage, https://github.com/drewwint/resmod
License-File: LICENSE
Requires-Dist: numpy
Requires-Dist: pandas
Requires-Dist: scipy
Requires-Dist: matplotlib
Requires-Dist: statsmodels
Requires-Dist: patsy
Dynamic: license-file
